mcp_server.py
mcp_couchbase-0.3.0.dist-info/licenses/LICENSE
mcp_couchbase-0.3.0.dist-info/METADATA
mcp_couchbase-0.3.0.dist-info/WHEEL
mcp_couchbase-0.3.0.dist-info/entry_points.txt
mcp_couchbase-0.3.0.dist-info/top_level.txt
mcp_couchbase-0.3.0.dist-info/RECORD
