Metadata-Version: 2.4
Name: mcp-couchbase
Version: 0.3.0
Summary: Couchbase MCP Server - The Developer Data Platform for Critical Applications in Our AI World
Author-email: Nithish Raghunandanan <devadvocates@couchbase.com>
License-Expression: Apache-2.0
Project-URL: Homepage, https://github.com/Couchbase-Ecosystem/mcp-server-couchbase
Project-URL: Documentation, https://github.com/Couchbase-Ecosystem/mcp-server-couchbase#readme
Project-URL: Issues, https://github.com/Couchbase-Ecosystem/mcp-server-couchbase/issues
Classifier: Development Status :: 4 - Beta
Classifier: Programming Language :: Python :: 3
Classifier: Topic :: Database
Requires-Python: >=3.10
License-File: LICENSE
Requires-Dist: click>=8.1.8
Requires-Dist: couchbase>=4.3.5
Requires-Dist: lark-sqlpp>=0.0.1
Requires-Dist: mcp[cli]>=1.5.0
Requires-Dist: python-dotenv>=1.0.0
Dynamic: license-file
